du_fake_header/__init__.py
du_fake_header/datasets.py
du_fake_header/generator.py
du_fake_header/models.py
du_fake_header-0.1.0.dist-info/licenses/LICENSE
du_fake_header-0.1.0.dist-info/METADATA
du_fake_header-0.1.0.dist-info/WHEEL
du_fake_header-0.1.0.dist-info/top_level.txt
du_fake_header-0.1.0.dist-info/RECORD
