Metadata-Version: 2.4
Name: du-fake-header
Version: 0.1.0
Summary: 生成随机但真实的 HTTP 请求头，支持 Chrome、Edge、Firefox、Safari 浏览器
Author: dyz
License: MIT
Keywords: http,headers,fake,user-agent
Requires-Python: >=3.11
License-File: LICENSE
Requires-Dist: pydantic>=2.12.0
Dynamic: license-file
